{"Title": "Report: Four teams expressing interest in Nick Easton, including Saints", "Url": "https://sports.yahoo.com/report-four-teams-expressing-interest-061423761.html", "Image": "https://www.bing.com/th?id=OVFT.YHVV0xUIBXxv3hwnkIfY3i&pid=News", "Description": "Veteran offensive lineman Nick Easton has drawn interest from four teams after his release from the New Orleans Saints two weeks ago, according to NFL reporter Josina Anderson. Easton was cut by the Saints in a salary cap move as they were well over the cap.", "Author": "Yahoo! Sports"}