{"Title": "DeMarcus Cousins released by Rockets; is he a fit for Boston?", "Url": "https://sports.yahoo.com/demarcus-cousins-released-rockets-fit-174530131.html?src=rss", "Image": "https://www.bing.com/th?id=OVFT.vw7wG2QdC4K6733OixoroC&pid=News", "Description": "The Houston Rockets decided to do DeMarcus Cousins a solid and release the veteran big man so he can find a new home with a contender, per the Athletic\u2019s Shams Charania. They even guaranteed his salary as a way to thank him for his professionalism while with the Rockets this season,", "Author": "Yahoo! Sports"}