{"Title": "Report: \u201cMutual\u201d interest between Dolphins, Aaron Jones", "Url": "https://www.msn.com/en-us/sports/nfl/report-e2-80-9cmutual-e2-80-9d-interest-between-dolphins-aaron-jones/ar-BB1dXiP0", "Image": "https://www.bing.com/th?id=OVFT.zTNKveALd_IfAYHmCkxP3S&pid=News", "Description": "Green Bay Packers running back Aaron Jones is expected to be the top running back on the free agent market when the new league year begins next month. According to Barry Jackson of the Miami Herald, when Jones hits the market the Miami Dolphins will be one of the teams pursuing him.", "Author": "NBC Sports on MSN.com"}