{"Title": "Hawks vs. Cavaliers odds, line, spread: 2021 NBA picks, Feb. 23 predictions from model on 85-49 roll", "Url": "https://www.msn.com/en-us/sports/nba/hawks-vs-cavaliers-odds-line-spread-2021-nba-picks-feb-23-predictions-from-model-on-85-49-roll/ar-BB1dWw6s", "Image": "https://www.bing.com/th?id=OVFT.Bzn2U2P7LB9BIEBQcOh4ci&pid=News", "Description": "William Hill Sportsbook lists Atlanta as an eight-point favorite, while the over-under is 228 in the latest Hawks vs. Cavaliers odds. Before finalizing any Cavaliers vs. Hawks picks, be sure to see the NBA predictions and betting advice from SportsLine's proven computer model.", "Author": "CBSSports.com on MSN.com"}