{"Title": "Dallas Mavs Defeat Memphis Grizzlies, Doncic loses franchise-record streak", "Url": "https://www.si.com/nba/mavericks/news/dallas-mavs-defeat-memphis-grizzlies-doncic-loses-franchise-record-streak", "Image": "https://www.bing.com/th?id=OVFT.5o52JZWMcBTjOif-xsFFRS&pid=News", "Description": "After eight days of severe Texas weather-induced rest, the Dallas Mavericks beat the Memphis Grizzlies, 102-92 on Monday night. With the extra time off, the Mavs utilized valuable practice time to work on communication and their 27th ranked", "Author": "Sports Illustrated"}